pdffile/__init__.py
pdffile/pdffile.py
comicbox_pdffile-0.2.5.dist-info/METADATA
comicbox_pdffile-0.2.5.dist-info/WHEEL
comicbox_pdffile-0.2.5.dist-info/licenses/LICENSE
comicbox_pdffile-0.2.5.dist-info/RECORD
