Metadata-Version: 2.4
Name: comicbox-pdffile
Version: 0.2.5
Summary: A ZipFile like API for PyMuPDF
Project-URL: News, https://github.com/ajslater/comicbox-pdffile
Project-URL: Report Issues, https://github.com/ajslater/comicbox-pdffile/issues
Project-URL: homepage, https://github.com/ajslater/comicbox-pdffile
Project-URL: repository, https://github.com/ajslater/comicbox-pdffile
Project-URL: documentation, https://github.com/ajslater/comicbox-pdffile
Author-email: AJ Slater <aj@slater.net>
License: GPL-3.0-only
License-File: LICENSE
Classifier: Development Status :: 5 - Production/Stable
Classifier: License :: OSI Approved :: GNU General Public License v3 (GPLv3)
Classifier: Natural Language :: English
Classifier: Operating System :: OS Independent
Classifier: Programming Language :: Python :: 3 :: Only
Requires-Python: <4.0,>=3.9
Requires-Dist: filetype<2.0.0,>=1.2.0
Requires-Dist: pymupdf<2.0.0,>=1.24.0
Requires-Dist: python-dateutil>=2.9.0.post0
Requires-Dist: typing-extensions>=4.13.2
